edgarcli/__init__.py
edgarcli/config.py
edgarcli/main.py
edgarcli/utils.py
edgarcli/commands/__init__.py
edgarcli/commands/company.py
edgarcli/commands/config.py
edgarcli/commands/filing.py
edgarcli/commands/filings.py
edgarcli/commands/statements.py
edgarcli-0.1.1.dist-info/METADATA
edgarcli-0.1.1.dist-info/WHEEL
edgarcli-0.1.1.dist-info/entry_points.txt
edgarcli-0.1.1.dist-info/licenses/LICENSE
edgarcli-0.1.1.dist-info/RECORD
