Metadata-Version: 2.4
Name: edgarcli
Version: 0.1.1
Summary: CLI wrapper for edgartools - SEC EDGAR data access from the command line
Project-URL: Homepage, https://github.com/ouachitalabs/edgarcli
Project-URL: Repository, https://github.com/ouachitalabs/edgarcli
Project-URL: Issues, https://github.com/ouachitalabs/edgarcli/issues
Project-URL: Documentation, https://github.com/dgunning/edgartools
Author-email: John McCrary <john@ouachitalabs.com>
License: MIT
License-File: LICENSE
Keywords: 10-k,10-q,cli,edgar,finance,financial-data,sec
Classifier: Development Status :: 4 - Beta
Classifier: Environment :: Console
Classifier: Intended Audience :: Developers
Classifier: Intended Audience :: Financial and Insurance Industry
Classifier: License :: OSI Approved :: MIT License
Classifier: Programming Language :: Python :: 3
Classifier: Programming Language :: Python :: 3.10
Classifier: Programming Language :: Python :: 3.11
Classifier: Programming Language :: Python :: 3.12
Classifier: Programming Language :: Python :: 3.13
Classifier: Topic :: Office/Business :: Financial
Classifier: Topic :: Software Development :: Libraries :: Python Modules
Classifier: Typing :: Typed
Requires-Python: >=3.10
Requires-Dist: click>=8.1.7
Requires-Dist: edgartools>=4.20.1
Requires-Dist: ipython>=8.12.0
